{"stats":{"minecraft:broken":{"minecraft:diamond_shovel":2},"minecraft:used":{"minecraft:water_bucket":87,"minecraft:stripped_birch_log":1073,"minecraft:stone":511,"minecraft:quartz_stairs":66,"minecraft:tube_coral":2,"minecraft:oak_leaves":23,"minecraft:torch":79,"minecraft:pink_concrete":394,"minecraft:dirt":2153,"minecraft:anvil":5,"minecraft:vine":28,"minecraft:sponge":16,"minecraft:salmon_bucket":2,"minecraft:white_bed":13,"minecraft:acacia_sapling":5,"minecraft:fire_coral":1,"minecraft:granite":6,"minecraft:oak_log":51,"minecraft:lava_bucket":1,"minecraft:diamond_shovel":10070,"minecraft:quartz_pillar":69,"minecraft:dark_oak_log":27,"minecraft:grass_block":580,"minecraft:stone_button":1,"minecraft:sign":11,"minecraft:stone_slab":124,"minecraft:smooth_quartz":869,"minecraft:spruce_sapling":4,"minecraft:diamond_sword":100,"minecraft:cobblestone":185,"minecraft:oak_sapling":4,"minecraft:cooked_porkchop":6,"minecraft:white_stained_glass_pane":10,"minecraft:white_stained_glass":14,"minecraft:bucket":41,"minecraft:sea_pickle":4,"minecraft:bone_meal":47,"minecraft:horn_coral_fan":1,"minecraft:cobweb":2,"minecraft:gray_stained_glass":11,"minecraft:dark_oak_sapling":12},"minecraft:killed":{"minecraft:pig":1,"minecraft:spider":4,"minecraft:creeper":14,"minecraft:skeleton":6,"minecraft:zombie":8,"minecraft:cow":5},"minecraft:custom":{"minecraft:mob_kills":38,"minecraft:play_one_minute":276317,"minecraft:leave_game":13,"minecraft:sleep_in_bed":12,"minecraft:time_since_death":15411,"minecraft:climb_one_cm":5280,"minecraft:time_since_rest":561,"minecraft:sprint_one_cm":629124,"minecraft:damage_taken":290,"minecraft:walk_one_cm":1087380,"minecraft:drop":15,"minecraft:damage_dealt":6899,"minecraft:swim_one_cm":6491,"minecraft:fly_one_cm":1295720,"minecraft:crouch_one_cm":18684,"minecraft:deaths":1,"minecraft:sneak_time":4875,"minecraft:walk_under_water_one_cm":50777,"minecraft:jump":2034,"minecraft:walk_on_water_one_cm":24333,"minecraft:fall_one_cm":9842},"minecraft:mined":{"minecraft:white_bed":13,"minecraft:grass_block":7267,"minecraft:poppy":2,"minecraft:sugar_cane":3,"minecraft:grass":164,"minecraft:sand":42,"minecraft:dirt":2577},"minecraft:dropped":{"minecraft:anvil":1,"minecraft:wheat_seeds":1,"minecraft:grass_block":1,"minecraft:poppy":3,"minecraft:dirt":513,"minecraft:sand":9,"minecraft:dandelion":9},"minecraft:picked_up":{"minecraft:anvil":1,"minecraft:leather":3,"minecraft:gunpowder":12,"minecraft:dirt":6904,"minecraft:string":5,"minecraft:bone":6,"minecraft:wheat_seeds":243,"minecraft:beef":9,"minecraft:poppy":29,"minecraft:sugar_cane":4,"minecraft:egg":1,"minecraft:torch":30,"minecraft:dandelion":20,"minecraft:porkchop":2,"minecraft:sand":36,"minecraft:white_bed":2,"minecraft:grass_block":1,"minecraft:arrow":5,"minecraft:rotten_flesh":6,"minecraft:oak_sapling":3,"minecraft:oxeye_daisy":16}},"DataVersion":1631}